django_email_log-1.5.0.dist-info/licenses/AUTHORS.rst
django_email_log-1.5.0.dist-info/licenses/LICENSE
email_log/__init__.py
email_log/admin.py
email_log/apps.py
email_log/backends.py
email_log/conf.py
email_log/models.py
email_log/signal_handlers.py
email_log/migrations/0001_initial.py
email_log/migrations/0002_email.py
email_log/migrations/0003_email_html_message_attachment.py
email_log/migrations/0004_alter_attachment_file.py
email_log/migrations/0005_email_bcc_recipients_email_cc_recipients.py
email_log/migrations/0006_email_extra_headers_email_reply_to.py
email_log/migrations/0007_log.py
email_log/migrations/__init__.py
django_email_log-1.5.0.dist-info/METADATA
django_email_log-1.5.0.dist-info/WHEEL
django_email_log-1.5.0.dist-info/top_level.txt
django_email_log-1.5.0.dist-info/RECORD
