Metadata-Version: 2.4
Name: django-email-log
Version: 1.5.0
Summary: Django email backend that logs all emails
Author-email: Trey Hunner <trey@treyhunner.com>
Project-URL: Homepage, https://github.com/treyhunner/django-email-log
Classifier: Development Status :: 5 - Production/Stable
Classifier: Environment :: Web Environment
Classifier: Intended Audience :: Developers
Classifier: License :: OSI Approved :: MIT License
Classifier: Operating System :: OS Independent
Classifier: Programming Language :: Python
Classifier: Programming Language :: Python :: 3
Classifier: Programming Language :: Python :: 3.8
Classifier: Programming Language :: Python :: 3.9
Classifier: Programming Language :: Python :: 3.10
Classifier: Programming Language :: Python :: 3.11
Classifier: Programming Language :: Python :: 3.12
Classifier: Programming Language :: Python :: 3.13
Classifier: Framework :: Django
Classifier: Framework :: Django :: 4.2
Classifier: Framework :: Django :: 5.0
Classifier: Framework :: Django :: 5.1
Classifier: Framework :: Django :: 5.2
License-File: LICENSE
License-File: AUTHORS.rst
Requires-Dist: Django>=2.2.0
Provides-Extra: build
Requires-Dist: build; extra == "build"
Requires-Dist: twine; extra == "build"
Provides-Extra: docs
Requires-Dist: Sphinx; extra == "docs"
Provides-Extra: test
Requires-Dist: coverage; extra == "test"
Requires-Dist: django-anymail; extra == "test"
Requires-Dist: pytest; extra == "test"
Requires-Dist: pytest-cov; extra == "test"
Requires-Dist: pytest-django; extra == "test"
Requires-Dist: tox; extra == "test"
Dynamic: license-file
